funapi/__init__.py
funnote-0.0.1.dist-info/LICENSE
funnote-0.0.1.dist-info/METADATA
funnote-0.0.1.dist-info/WHEEL
funnote-0.0.1.dist-info/entry_points.txt
funnote-0.0.1.dist-info/top_level.txt
funnote-0.0.1.dist-info/RECORD
