Metadata-Version: 2.1
Name: funnote
Version: 0.0.1
Summary: funnote
Home-page: https://github.com/farfarfun/funnote
Author: bingtao
Author-email: 1007530194@qq.com
License-File: LICENSE
Requires-Dist: funpypi
Requires-Dist: funfile
Requires-Dist: requests
Requires-Dist: tqdm
